{
  "annotations": {
    "list": [
      {
        "builtIn": 1,
        "datasource": {
          "type": "grafana",
          "uid": "-- Grafana --"
        },
        "enable": true,
        "hide": true,
        "iconColor": "rgba(0, 211, 255, 1)",
        "name": "Annotations & Alerts",
        "type": "dashboard"
      }
    ]
  },
  "editable": true,
  "fiscalYearStartMonth": 0,
  "graphTooltip": 0,
  "id": null,
  "links": [],
  "liveNow": false,
  "panels": [
    {
      "id": 1,
      "type": "row",
      "title": "Overview",
      "gridPos": {
        "h": 1,
        "w": 24,
        "x": 0,
        "y": 0
      },
      "collapsed": false,
      "panels": []
    },
    {
      "id": 2,
      "type": "stat",
      "title": "Exporter Up",
      "datasource": {
        "type": "prometheus",
        "uid": "${DS_PROMETHEUS}"
      },
      "gridPos": {
        "h": 4,
        "w": 4,
        "x": 0,
        "y": 1
      },
      "targets": [
        {
          "datasource": {
            "type": "prometheus",
            "uid": "${DS_PROMETHEUS}"
          },
          "editorMode": "code",
          "expr": "dell_me_exporter_up{job=~\"$job\",instance=~\"$instance\"}",
          "legendFormat": "",
          "range": false,
          "refId": "A",
          "instant": true,
          "format": "time_series"
        }
      ],
      "options": {
        "colorMode": "background",
        "graphMode": "none",
        "justifyMode": "center",
        "orientation": "auto",
        "reduceOptions": {
          "calcs": [
            "lastNotNull"
          ],
          "fields": "",
          "values": false
        },
        "textMode": "auto",
        "wideLayout": true
      },
      "fieldConfig": {
        "defaults": {
          "unit": "short",
          "decimals": 0,
          "thresholds": {
            "mode": "absolute",
            "steps": [
              {
                "color": "red",
                "value": null
              },
              {
                "color": "green",
                "value": 1
              }
            ]
          }
        },
        "overrides": []
      }
    },
    {
      "id": 3,
      "type": "stat",
      "title": "System Health",
      "datasource": {
        "type": "prometheus",
        "uid": "${DS_PROMETHEUS}"
      },
      "gridPos": {
        "h": 4,
        "w": 4,
        "x": 4,
        "y": 1
      },
      "targets": [
        {
          "datasource": {
            "type": "prometheus",
            "uid": "${DS_PROMETHEUS}"
          },
          "editorMode": "code",
          "expr": "dell_me_system_health{job=~\"$job\",instance=~\"$instance\"}",
          "legendFormat": "",
          "range": false,
          "refId": "A",
          "instant": true,
          "format": "time_series"
        }
      ],
      "options": {
        "colorMode": "background",
        "graphMode": "none",
        "justifyMode": "center",
        "orientation": "auto",
        "reduceOptions": {
          "calcs": [
            "lastNotNull"
          ],
          "fields": "",
          "values": false
        },
        "textMode": "auto",
        "wideLayout": true
      },
      "fieldConfig": {
        "defaults": {
          "unit": "short",
          "decimals": 0,
          "thresholds": {
            "mode": "absolute",
            "steps": [
              {
                "color": "red",
                "value": null
              },
              {
                "color": "green",
                "value": 1
              }
            ]
          }
        },
        "overrides": []
      }
    },
    {
      "id": 4,
      "type": "stat",
      "title": "Active Alerts",
      "datasource": {
        "type": "prometheus",
        "uid": "${DS_PROMETHEUS}"
      },
      "gridPos": {
        "h": 4,
        "w": 4,
        "x": 8,
        "y": 1
      },
      "targets": [
        {
          "datasource": {
            "type": "prometheus",
            "uid": "${DS_PROMETHEUS}"
          },
          "editorMode": "code",
          "expr": "dell_me_active_alerts{job=~\"$job\",instance=~\"$instance\"}",
          "legendFormat": "",
          "range": false,
          "refId": "A",
          "instant": true,
          "format": "time_series"
        }
      ],
      "options": {
        "colorMode": "background",
        "graphMode": "none",
        "justifyMode": "center",
        "orientation": "auto",
        "reduceOptions": {
          "calcs": [
            "lastNotNull"
          ],
          "fields": "",
          "values": false
        },
        "textMode": "auto",
        "wideLayout": true
      },
      "fieldConfig": {
        "defaults": {
          "unit": "short",
          "decimals": 0,
          "thresholds": {
            "mode": "absolute",
            "steps": [
              {
                "color": "green",
                "value": null
              },
              {
                "color": "yellow",
                "value": 1
              },
              {
                "color": "red",
                "value": 5
              }
            ]
          }
        },
        "overrides": []
      }
    },
    {
      "id": 5,
      "type": "stat",
      "title": "Collection Duration",
      "datasource": {
        "type": "prometheus",
        "uid": "${DS_PROMETHEUS}"
      },
      "gridPos": {
        "h": 4,
        "w": 4,
        "x": 12,
        "y": 1
      },
      "targets": [
        {
          "datasource": {
            "type": "prometheus",
            "uid": "${DS_PROMETHEUS}"
          },
          "editorMode": "code",
          "expr": "dell_me_collection_duration_seconds{job=~\"$job\",instance=~\"$instance\"}",
          "legendFormat": "",
          "range": false,
          "refId": "A",
          "instant": true,
          "format": "time_series"
        }
      ],
      "options": {
        "colorMode": "background",
        "graphMode": "none",
        "justifyMode": "center",
        "orientation": "auto",
        "reduceOptions": {
          "calcs": [
            "lastNotNull"
          ],
          "fields": "",
          "values": false
        },
        "textMode": "auto",
        "wideLayout": true
      },
      "fieldConfig": {
        "defaults": {
          "unit": "s",
          "decimals": 1,
          "thresholds": {
            "mode": "absolute",
            "steps": [
              {
                "color": "green",
                "value": null
              },
              {
                "color": "yellow",
                "value": 30
              },
              {
                "color": "red",
                "value": 60
              }
            ]
          }
        },
        "overrides": []
      }
    },
    {
      "id": 6,
      "type": "stat",
      "title": "Collection Errors",
      "datasource": {
        "type": "prometheus",
        "uid": "${DS_PROMETHEUS}"
      },
      "gridPos": {
        "h": 4,
        "w": 4,
        "x": 16,
        "y": 1
      },
      "targets": [
        {
          "datasource": {
            "type": "prometheus",
            "uid": "${DS_PROMETHEUS}"
          },
          "editorMode": "code",
          "expr": "increase(dell_me_collection_errors_total{job=~\"$job\",instance=~\"$instance\"}[$__range])",
          "legendFormat": "",
          "range": false,
          "refId": "A",
          "instant": true,
          "format": "time_series"
        }
      ],
      "options": {
        "colorMode": "background",
        "graphMode": "none",
        "justifyMode": "center",
        "orientation": "auto",
        "reduceOptions": {
          "calcs": [
            "lastNotNull"
          ],
          "fields": "",
          "values": false
        },
        "textMode": "auto",
        "wideLayout": true
      },
      "fieldConfig": {
        "defaults": {
          "unit": "short",
          "decimals": 0,
          "thresholds": {
            "mode": "absolute",
            "steps": [
              {
                "color": "green",
                "value": null
              },
              {
                "color": "red",
                "value": 1
              }
            ]
          }
        },
        "overrides": []
      }
    },
    {
      "id": 7,
      "type": "stat",
      "title": "Last Success Age",
      "datasource": {
        "type": "prometheus",
        "uid": "${DS_PROMETHEUS}"
      },
      "gridPos": {
        "h": 4,
        "w": 4,
        "x": 20,
        "y": 1
      },
      "targets": [
        {
          "datasource": {
            "type": "prometheus",
            "uid": "${DS_PROMETHEUS}"
          },
          "editorMode": "code",
          "expr": "time() - dell_me_last_success_unixtime{job=~\"$job\",instance=~\"$instance\"}",
          "legendFormat": "",
          "range": false,
          "refId": "A",
          "instant": true,
          "format": "time_series"
        }
      ],
      "options": {
        "colorMode": "background",
        "graphMode": "none",
        "justifyMode": "center",
        "orientation": "auto",
        "reduceOptions": {
          "calcs": [
            "lastNotNull"
          ],
          "fields": "",
          "values": false
        },
        "textMode": "auto",
        "wideLayout": true
      },
      "fieldConfig": {
        "defaults": {
          "unit": "s",
          "decimals": 0,
          "thresholds": {
            "mode": "absolute",
            "steps": [
              {
                "color": "green",
                "value": null
              },
              {
                "color": "yellow",
                "value": 180
              },
              {
                "color": "red",
                "value": 600
              }
            ]
          }
        },
        "overrides": []
      }
    },
    {
      "id": 8,
      "type": "table",
      "title": "Collector Status",
      "datasource": {
        "type": "prometheus",
        "uid": "${DS_PROMETHEUS}"
      },
      "gridPos": {
        "h": 7,
        "w": 12,
        "x": 0,
        "y": 5
      },
      "targets": [
        {
          "datasource": {
            "type": "prometheus",
            "uid": "${DS_PROMETHEUS}"
          },
          "editorMode": "code",
          "expr": "dell_me_collector_up{job=~\"$job\",instance=~\"$instance\"}",
          "legendFormat": "",
          "range": false,
          "refId": "A",
          "instant": true,
          "format": "table"
        }
      ],
      "options": {
        "showHeader": true,
        "cellHeight": "sm",
        "footer": {
          "show": false,
          "reducer": [
            "sum"
          ],
          "countRows": false,
          "fields": ""
        }
      },
      "fieldConfig": {
        "defaults": {
          "custom": {
            "align": "auto",
            "cellOptions": {
              "type": "auto"
            },
            "inspect": false
          }
        },
        "overrides": []
      }
    },
    {
      "id": 9,
      "type": "timeseries",
      "title": "Collector Duration",
      "datasource": {
        "type": "prometheus",
        "uid": "${DS_PROMETHEUS}"
      },
      "gridPos": {
        "h": 7,
        "w": 12,
        "x": 12,
        "y": 5
      },
      "targets": [
        {
          "datasource": {
            "type": "prometheus",
            "uid": "${DS_PROMETHEUS}"
          },
          "editorMode": "code",
          "expr": "dell_me_collector_duration_seconds{job=~\"$job\",instance=~\"$instance\"}",
          "legendFormat": "{{collector}}",
          "range": true,
          "refId": "A"
        }
      ],
      "options": {
        "legend": {
          "displayMode": "table",
          "placement": "bottom",
          "showLegend": true
        },
        "tooltip": {
          "mode": "multi",
          "sort": "none"
        }
      },
      "fieldConfig": {
        "defaults": {
          "unit": "s",
          "custom": {
            "drawStyle": "line",
            "lineInterpolation": "linear",
            "lineWidth": 1,
            "fillOpacity": 10,
            "showPoints": "never",
            "spanNulls": false
          }
        },
        "overrides": []
      }
    },
    {
      "id": 10,
      "type": "row",
      "title": "Capacity",
      "gridPos": {
        "h": 1,
        "w": 24,
        "x": 0,
        "y": 12
      },
      "collapsed": false,
      "panels": []
    },
    {
      "id": 11,
      "type": "gauge",
      "title": "Pool Used Percent",
      "datasource": {
        "type": "prometheus",
        "uid": "${DS_PROMETHEUS}"
      },
      "gridPos": {
        "h": 8,
        "w": 8,
        "x": 0,
        "y": 13
      },
      "targets": [
        {
          "datasource": {
            "type": "prometheus",
            "uid": "${DS_PROMETHEUS}"
          },
          "editorMode": "code",
          "expr": "dell_me_pool_used_percent{job=~\"$job\",instance=~\"$instance\"}",
          "legendFormat": "{{pool}}",
          "range": false,
          "refId": "A",
          "instant": true,
          "format": "time_series"
        }
      ],
      "options": {
        "orientation": "auto",
        "reduceOptions": {
          "calcs": [
            "lastNotNull"
          ],
          "fields": "",
          "values": false
        },
        "showThresholdLabels": false,
        "showThresholdMarkers": true
      },
      "fieldConfig": {
        "defaults": {
          "unit": "percent",
          "min": 0,
          "max": 100,
          "thresholds": {
            "mode": "absolute",
            "steps": [
              {
                "color": "green",
                "value": null
              },
              {
                "color": "yellow",
                "value": 75
              },
              {
                "color": "red",
                "value": 90
              }
            ]
          }
        },
        "overrides": []
      }
    },
    {
      "id": 12,
      "type": "timeseries",
      "title": "Pool Capacity",
      "datasource": {
        "type": "prometheus",
        "uid": "${DS_PROMETHEUS}"
      },
      "gridPos": {
        "h": 8,
        "w": 8,
        "x": 8,
        "y": 13
      },
      "targets": [
        {
          "datasource": {
            "type": "prometheus",
            "uid": "${DS_PROMETHEUS}"
          },
          "editorMode": "code",
          "expr": "dell_me_pool_size_bytes{job=~\"$job\",instance=~\"$instance\"} or dell_me_pool_used_bytes{job=~\"$job\",instance=~\"$instance\"} or dell_me_pool_free_bytes{job=~\"$job\",instance=~\"$instance\"}",
          "legendFormat": "{{__name__}} {{pool}}",
          "range": true,
          "refId": "A"
        }
      ],
      "options": {
        "legend": {
          "displayMode": "table",
          "placement": "bottom",
          "showLegend": true
        },
        "tooltip": {
          "mode": "multi",
          "sort": "none"
        }
      },
      "fieldConfig": {
        "defaults": {
          "unit": "bytes",
          "custom": {
            "drawStyle": "line",
            "lineInterpolation": "linear",
            "lineWidth": 1,
            "fillOpacity": 10,
            "showPoints": "never",
            "spanNulls": false
          }
        },
        "overrides": []
      }
    },
    {
      "id": 13,
      "type": "table",
      "title": "Volumes",
      "datasource": {
        "type": "prometheus",
        "uid": "${DS_PROMETHEUS}"
      },
      "gridPos": {
        "h": 8,
        "w": 8,
        "x": 16,
        "y": 13
      },
      "targets": [
        {
          "datasource": {
            "type": "prometheus",
            "uid": "${DS_PROMETHEUS}"
          },
          "editorMode": "code",
          "expr": "dell_me_volume_size_bytes{job=~\"$job\",instance=~\"$instance\"}",
          "legendFormat": "",
          "range": false,
          "refId": "A",
          "instant": true,
          "format": "table"
        }
      ],
      "options": {
        "showHeader": true,
        "cellHeight": "sm",
        "footer": {
          "show": false,
          "reducer": [
            "sum"
          ],
          "countRows": false,
          "fields": ""
        }
      },
      "fieldConfig": {
        "defaults": {
          "custom": {
            "align": "auto",
            "cellOptions": {
              "type": "auto"
            },
            "inspect": false
          }
        },
        "overrides": []
      }
    },
    {
      "id": 14,
      "type": "row",
      "title": "Controllers and Ports",
      "gridPos": {
        "h": 1,
        "w": 24,
        "x": 0,
        "y": 21
      },
      "collapsed": false,
      "panels": []
    },
    {
      "id": 15,
      "type": "table",
      "title": "Controller Health",
      "datasource": {
        "type": "prometheus",
        "uid": "${DS_PROMETHEUS}"
      },
      "gridPos": {
        "h": 8,
        "w": 8,
        "x": 0,
        "y": 22
      },
      "targets": [
        {
          "datasource": {
            "type": "prometheus",
            "uid": "${DS_PROMETHEUS}"
          },
          "editorMode": "code",
          "expr": "dell_me_controller_health{job=~\"$job\",instance=~\"$instance\"} or dell_me_controller_operational{job=~\"$job\",instance=~\"$instance\"} or dell_me_controller_redundant{job=~\"$job\",instance=~\"$instance\"}",
          "legendFormat": "",
          "range": false,
          "refId": "A",
          "instant": true,
          "format": "table"
        }
      ],
      "options": {
        "showHeader": true,
        "cellHeight": "sm",
        "footer": {
          "show": false,
          "reducer": [
            "sum"
          ],
          "countRows": false,
          "fields": ""
        }
      },
      "fieldConfig": {
        "defaults": {
          "custom": {
            "align": "auto",
            "cellOptions": {
              "type": "auto"
            },
            "inspect": false
          }
        },
        "overrides": []
      }
    },
    {
      "id": 16,
      "type": "timeseries",
      "title": "Host Port Speed",
      "datasource": {
        "type": "prometheus",
        "uid": "${DS_PROMETHEUS}"
      },
      "gridPos": {
        "h": 8,
        "w": 8,
        "x": 8,
        "y": 22
      },
      "targets": [
        {
          "datasource": {
            "type": "prometheus",
            "uid": "${DS_PROMETHEUS}"
          },
          "editorMode": "code",
          "expr": "dell_me_host_port_speed_gbps{job=~\"$job\",instance=~\"$instance\"}",
          "legendFormat": "{{controller}} {{port}} {{media}}",
          "range": true,
          "refId": "A"
        }
      ],
      "options": {
        "legend": {
          "displayMode": "table",
          "placement": "bottom",
          "showLegend": true
        },
        "tooltip": {
          "mode": "multi",
          "sort": "none"
        }
      },
      "fieldConfig": {
        "defaults": {
          "unit": "Gbits",
          "custom": {
            "drawStyle": "line",
            "lineInterpolation": "linear",
            "lineWidth": 1,
            "fillOpacity": 10,
            "showPoints": "never",
            "spanNulls": false
          }
        },
        "overrides": []
      }
    },
    {
      "id": 17,
      "type": "table",
      "title": "Port Link State",
      "datasource": {
        "type": "prometheus",
        "uid": "${DS_PROMETHEUS}"
      },
      "gridPos": {
        "h": 8,
        "w": 8,
        "x": 16,
        "y": 22
      },
      "targets": [
        {
          "datasource": {
            "type": "prometheus",
            "uid": "${DS_PROMETHEUS}"
          },
          "editorMode": "code",
          "expr": "dell_me_host_port_up{job=~\"$job\",instance=~\"$instance\"} or dell_me_expander_port_up{job=~\"$job\",instance=~\"$instance\"} or dell_me_management_link_up{job=~\"$job\",instance=~\"$instance\"}",
          "legendFormat": "",
          "range": false,
          "refId": "A",
          "instant": true,
          "format": "table"
        }
      ],
      "options": {
        "showHeader": true,
        "cellHeight": "sm",
        "footer": {
          "show": false,
          "reducer": [
            "sum"
          ],
          "countRows": false,
          "fields": ""
        }
      },
      "fieldConfig": {
        "defaults": {
          "custom": {
            "align": "auto",
            "cellOptions": {
              "type": "auto"
            },
            "inspect": false
          }
        },
        "overrides": []
      }
    },
    {
      "id": 18,
      "type": "row",
      "title": "Disks",
      "gridPos": {
        "h": 1,
        "w": 24,
        "x": 0,
        "y": 30
      },
      "collapsed": false,
      "panels": []
    },
    {
      "id": 19,
      "type": "table",
      "title": "Disk Health",
      "datasource": {
        "type": "prometheus",
        "uid": "${DS_PROMETHEUS}"
      },
      "gridPos": {
        "h": 8,
        "w": 8,
        "x": 0,
        "y": 31
      },
      "targets": [
        {
          "datasource": {
            "type": "prometheus",
            "uid": "${DS_PROMETHEUS}"
          },
          "editorMode": "code",
          "expr": "dell_me_disk_health{job=~\"$job\",instance=~\"$instance\"} or dell_me_disk_online{job=~\"$job\",instance=~\"$instance\"}",
          "legendFormat": "",
          "range": false,
          "refId": "A",
          "instant": true,
          "format": "table"
        }
      ],
      "options": {
        "showHeader": true,
        "cellHeight": "sm",
        "footer": {
          "show": false,
          "reducer": [
            "sum"
          ],
          "countRows": false,
          "fields": ""
        }
      },
      "fieldConfig": {
        "defaults": {
          "custom": {
            "align": "auto",
            "cellOptions": {
              "type": "auto"
            },
            "inspect": false
          }
        },
        "overrides": []
      }
    },
    {
      "id": 20,
      "type": "timeseries",
      "title": "Disk Temperature",
      "datasource": {
        "type": "prometheus",
        "uid": "${DS_PROMETHEUS}"
      },
      "gridPos": {
        "h": 8,
        "w": 8,
        "x": 8,
        "y": 31
      },
      "targets": [
        {
          "datasource": {
            "type": "prometheus",
            "uid": "${DS_PROMETHEUS}"
          },
          "editorMode": "code",
          "expr": "dell_me_disk_temperature_celsius{job=~\"$job\",instance=~\"$instance\"}",
          "legendFormat": "{{enclosure}}/{{slot}}",
          "range": true,
          "refId": "A"
        }
      ],
      "options": {
        "legend": {
          "displayMode": "table",
          "placement": "bottom",
          "showLegend": true
        },
        "tooltip": {
          "mode": "multi",
          "sort": "none"
        }
      },
      "fieldConfig": {
        "defaults": {
          "unit": "celsius",
          "custom": {
            "drawStyle": "line",
            "lineInterpolation": "linear",
            "lineWidth": 1,
            "fillOpacity": 10,
            "showPoints": "never",
            "spanNulls": false
          }
        },
        "overrides": []
      }
    },
    {
      "id": 21,
      "type": "table",
      "title": "Disk Inventory",
      "datasource": {
        "type": "prometheus",
        "uid": "${DS_PROMETHEUS}"
      },
      "gridPos": {
        "h": 8,
        "w": 8,
        "x": 16,
        "y": 31
      },
      "targets": [
        {
          "datasource": {
            "type": "prometheus",
            "uid": "${DS_PROMETHEUS}"
          },
          "editorMode": "code",
          "expr": "dell_me_disk_info{job=~\"$job\",instance=~\"$instance\"}",
          "legendFormat": "",
          "range": false,
          "refId": "A",
          "instant": true,
          "format": "table"
        }
      ],
      "options": {
        "showHeader": true,
        "cellHeight": "sm",
        "footer": {
          "show": false,
          "reducer": [
            "sum"
          ],
          "countRows": false,
          "fields": ""
        }
      },
      "fieldConfig": {
        "defaults": {
          "custom": {
            "align": "auto",
            "cellOptions": {
              "type": "auto"
            },
            "inspect": false
          }
        },
        "overrides": []
      }
    },
    {
      "id": 22,
      "type": "row",
      "title": "Alerts and Firmware",
      "gridPos": {
        "h": 1,
        "w": 24,
        "x": 0,
        "y": 39
      },
      "collapsed": false,
      "panels": []
    },
    {
      "id": 23,
      "type": "table",
      "title": "Unresolved Alerts by Severity",
      "datasource": {
        "type": "prometheus",
        "uid": "${DS_PROMETHEUS}"
      },
      "gridPos": {
        "h": 7,
        "w": 8,
        "x": 0,
        "y": 40
      },
      "targets": [
        {
          "datasource": {
            "type": "prometheus",
            "uid": "${DS_PROMETHEUS}"
          },
          "editorMode": "code",
          "expr": "dell_me_alerts{job=~\"$job\",instance=~\"$instance\"}",
          "legendFormat": "",
          "range": false,
          "refId": "A",
          "instant": true,
          "format": "table"
        }
      ],
      "options": {
        "showHeader": true,
        "cellHeight": "sm",
        "footer": {
          "show": false,
          "reducer": [
            "sum"
          ],
          "countRows": false,
          "fields": ""
        }
      },
      "fieldConfig": {
        "defaults": {
          "custom": {
            "align": "auto",
            "cellOptions": {
              "type": "auto"
            },
            "inspect": false
          }
        },
        "overrides": []
      }
    },
    {
      "id": 24,
      "type": "table",
      "title": "Firmware Versions",
      "datasource": {
        "type": "prometheus",
        "uid": "${DS_PROMETHEUS}"
      },
      "gridPos": {
        "h": 7,
        "w": 16,
        "x": 8,
        "y": 40
      },
      "targets": [
        {
          "datasource": {
            "type": "prometheus",
            "uid": "${DS_PROMETHEUS}"
          },
          "editorMode": "code",
          "expr": "dell_me_version_info{job=~\"$job\",instance=~\"$instance\"}",
          "legendFormat": "",
          "range": false,
          "refId": "A",
          "instant": true,
          "format": "table"
        }
      ],
      "options": {
        "showHeader": true,
        "cellHeight": "sm",
        "footer": {
          "show": false,
          "reducer": [
            "sum"
          ],
          "countRows": false,
          "fields": ""
        }
      },
      "fieldConfig": {
        "defaults": {
          "custom": {
            "align": "auto",
            "cellOptions": {
              "type": "auto"
            },
            "inspect": false
          }
        },
        "overrides": []
      }
    }
  ],
  "refresh": "1m",
  "schemaVersion": 39,
  "tags": [
    "dell",
    "me5",
    "storage",
    "prometheus"
  ],
  "templating": {
    "list": [
      {
        "name": "DS_PROMETHEUS",
        "type": "datasource",
        "query": "prometheus",
        "current": {
          "selected": false,
          "text": "Prometheus",
          "value": "prometheus"
        },
        "label": "Prometheus",
        "hide": 0
      },
      {
        "name": "job",
        "type": "query",
        "datasource": {
          "type": "prometheus",
          "uid": "${DS_PROMETHEUS}"
        },
        "query": {
          "query": "label_values(dell_me_exporter_up, job)",
          "refId": "PrometheusVariableQueryEditor-VariableQuery"
        },
        "refresh": 1,
        "sort": 1,
        "multi": true,
        "includeAll": true,
        "allValue": ".*",
        "current": {
          "selected": true,
          "text": "All",
          "value": "$__all"
        },
        "label": "job"
      },
      {
        "name": "instance",
        "type": "query",
        "datasource": {
          "type": "prometheus",
          "uid": "${DS_PROMETHEUS}"
        },
        "query": {
          "query": "label_values(dell_me_exporter_up{job=~\"$job\"}, instance)",
          "refId": "PrometheusVariableQueryEditor-VariableQuery"
        },
        "refresh": 1,
        "sort": 1,
        "multi": true,
        "includeAll": true,
        "allValue": ".*",
        "current": {
          "selected": true,
          "text": "All",
          "value": "$__all"
        },
        "label": "instance"
      }
    ]
  },
  "time": {
    "from": "now-6h",
    "to": "now"
  },
  "timepicker": {},
  "timezone": "browser",
  "title": "Dell PowerVault ME5",
  "uid": "dell-me5-ssh-exporter",
  "version": 1,
  "weekStart": ""
}
